pastasoss/__init__.py
pastasoss/soss_traces.py
pastasoss/wavecal.py
pastasoss/data/jwst_niriss_gr700xd_order1_trace_refmodel.txt
pastasoss/data/jwst_niriss_gr700xd_order2_trace_refmodel.txt
pastasoss/data/jwst_niriss_gr700xd_order2_trace_refmodel_002.txt
pastasoss/data/jwst_niriss_gr700xd_wavelength_model_order1.json
pastasoss/data/jwst_niriss_gr700xd_wavelength_model_order2.json
pastasoss/data/jwst_niriss_gr700xd_wavelength_model_order2_002.json
pastasoss-1.2.2.dist-info/LICENSE
pastasoss-1.2.2.dist-info/METADATA
pastasoss-1.2.2.dist-info/WHEEL
pastasoss-1.2.2.dist-info/top_level.txt
pastasoss-1.2.2.dist-info/RECORD
