Metadata-Version: 2.2
Name: pastasoss
Version: 1.2.2
Summary: Tool to predict the spectral traces for any NIRISS/SOSS observation
Author-email: Tyler Baines <tbaines@stsci.edu>
Requires-Python: >=3.10
License-File: LICENSE
Requires-Dist: jupyter>=1.0.0
Requires-Dist: numpy<2.0.0
Requires-Dist: matplotlib>=3.6.2
Requires-Dist: pytest>=7.2.0
Requires-Dist: scipy>=1.8.0
